casregnum/__init__.py
casregnum/casregnum.py
casregnum/casregnum.pyi
casregnum/py.typed
casregnum-1.1.2.dist-info/METADATA
casregnum-1.1.2.dist-info/WHEEL
casregnum-1.1.2.dist-info/licenses/LICENSE
casregnum-1.1.2.dist-info/RECORD
