Metadata-Version: 2.4
Name: casregnum
Version: 1.1.2
Summary: Python class to manage, check and sort CAS Registry Numbers® (CAS RN®)
Project-URL: Homepage, https://github.com/molshape/CASRegistryNumbers
Project-URL: Issues, https://github.com/molshape/CASRegistryNumbers/issues
Project-URL: Repository, https://github.com/molshape/CASRegistryNumbers.git
Author-email: Axel Müller <molshape@gmx.net>
Maintainer-email: Axel Müller <molshape@gmx.net>
License-Expression: MIT
License-File: LICENSE
Classifier: License :: OSI Approved :: MIT License
Classifier: Operating System :: OS Independent
Classifier: Programming Language :: Python :: 3.10
Classifier: Programming Language :: Python :: 3.11
Classifier: Programming Language :: Python :: 3.12
Classifier: Topic :: Scientific/Engineering :: Chemistry
Requires-Python: >=3.10
